ratio1/__init__.py
ratio1/_ver.py
ratio1/base_decentra_object.py
ratio1/plugins_manager_mixin.py
ratio1/base/__init__.py
ratio1/base/distributed_custom_code_presets.py
ratio1/base/generic_session.py
ratio1/base/instance.py
ratio1/base/pipeline.py
ratio1/base/plugin_template.py
ratio1/base/responses.py
ratio1/base/transaction.py
ratio1/base/webapp_pipeline.py
ratio1/base/payload/__init__.py
ratio1/base/payload/payload.py
ratio1/bc/__init__.py
ratio1/bc/base.py
ratio1/bc/chain.py
ratio1/bc/ec.py
ratio1/bc/evm.py
ratio1/certs/141.136.35.100.crt
ratio1/certs/195.35.29.4.crt
ratio1/certs/31.97.72.187.crt
ratio1/certs/51.15.142.167.crt
ratio1/certs/72.60.187.24.crt
ratio1/certs/72.60.81.67.crt
ratio1/certs/72.60.83.78.crt
ratio1/certs/__init__.py
ratio1/certs/a0d9818f.ala.eu-central-1.emqxsl.com.crt
ratio1/certs/r9092118.ala.eu-central-1.emqxsl.com.crt
ratio1/certs/s624dbd4.ala.us-east-1.emqxsl.com.crt
ratio1/cli/README.md
ratio1/cli/cli.py
ratio1/cli/cli_commands.py
ratio1/cli/nodes.py
ratio1/cli/oracles.py
ratio1/cli/package_update.py
ratio1/code_cheker/__init__.py
ratio1/code_cheker/base.py
ratio1/code_cheker/checker.py
ratio1/comm/__init__.py
ratio1/comm/amqp_wrapper.py
ratio1/comm/base_comm_wrapper.py
ratio1/comm/mqtt_wrapper.py
ratio1/const/README.md
ratio1/const/__init__.py
ratio1/const/apps.py
ratio1/const/base.py
ratio1/const/comms.py
ratio1/const/environment.py
ratio1/const/evm_net.py
ratio1/const/formatter.py
ratio1/const/heartbeat.py
ratio1/const/misc.py
ratio1/const/payload.py
ratio1/const/plugins/deeploy_const.py
ratio1/default/__init__.py
ratio1/default/instance/__init__.py
ratio1/default/instance/chain_dist_custom_job_01_plugin.py
ratio1/default/instance/custom_webapi_01_plugin.py
ratio1/default/instance/generic_http_01_plugin.py
ratio1/default/instance/net_mon_01_plugin.py
ratio1/default/instance/telegram_basic_bot_01_plugin.py
ratio1/default/instance/telegram_conversational_bot_01_plugin.py
ratio1/default/instance/view_scene_01_plugin.py
ratio1-3.4.125.dist-info/METADATA
ratio1-3.4.125.dist-info/WHEEL
ratio1-3.4.125.dist-info/entry_points.txt
ratio1-3.4.125.dist-info/licenses/LICENSE
ratio1-3.4.125.dist-info/RECORD
