Metadata-Version: 2.4
Name: ratio1
Version: 3.4.125
Summary: `ratio1` or Ration1 SDK is the Python SDK required for client app development for the Ratio1 ecosystem
Project-URL: Homepage, https://github.com/Ratio1/ratio1_sdk
Project-URL: Bug Tracker, https://github.com/Ratio1/ratio1_sdk/issues
Author-email: Andrei Ionut Damian <andrei.damian@ratio1.ai>, Cristan Bleotiu <cristian.bleotiu@ratio1.ai>
License-File: LICENSE
Classifier: License :: OSI Approved :: MIT License
Classifier: Operating System :: OS Independent
Classifier: Programming Language :: Python :: 3
Requires-Python: >=3.10
Requires-Dist: cryptography>=39.0.0
Requires-Dist: numpy
Requires-Dist: paho-mqtt
Requires-Dist: pandas
Requires-Dist: pika
Requires-Dist: psutil
Requires-Dist: pyaml
Requires-Dist: pyopenssl>=23.0.0
Requires-Dist: python-dateutil
Requires-Dist: web3>=7.0.0
